grobid/__init__.py
grobid/client.py
grobid/models/__init__.py
grobid/models/article.py
grobid/models/citation.py
grobid/models/form.py
grobid/models/misc.py
grobid/models/response.py
grobid/models/section.py
grobid/tei.py
grobid-0.1.3.dist-info/LICENSE
grobid-0.1.3.dist-info/WHEEL
grobid-0.1.3.dist-info/METADATA
grobid-0.1.3.dist-info/RECORD
