Metadata-Version: 2.1
Name: grobid
Version: 0.1.3
Summary: Python library for serializing GROBID TEI XML to dataclass
Home-page: https://github.com/ram02z/grobid
License: MIT
Keywords: GROBID,XML,dataclass
Author: Omar Zeghouani
Author-email: omarzeghouanii@gmail.com
Requires-Python: >=3.10,<4.0
Classifier: License :: OSI Approved :: MIT License
Classifier: Programming Language :: Python :: 3
Classifier: Programming Language :: Python :: 3.10
Classifier: Topic :: Software Development :: Libraries :: Python Modules
Provides-Extra: json
Requires-Dist: bs4 (>=0.0.1,<0.0.2)
Requires-Dist: httpx (>=0.23.0,<0.24.0)
Requires-Dist: lxml (>=4.9.1,<5.0.0)
Requires-Dist: mashumaro (>=3.0.3,<4.0.0); extra == "json"
Project-URL: Repository, https://github.com/ram02z/grobid
